pycp/__init__.py
pycp/main.py
pycp/progress.py
pycp/transfer.py
pycp-8.0.8.dist-info/AUTHORS
pycp-8.0.8.dist-info/COPYING.txt
pycp-8.0.8.dist-info/METADATA
pycp-8.0.8.dist-info/WHEEL
pycp-8.0.8.dist-info/entry_points.txt
pycp-8.0.8.dist-info/top_level.txt
pycp-8.0.8.dist-info/RECORD
