Metadata-Version: 2.1
Name: pycp
Version: 8.0.8
Summary: cp and mv with a progressbar
Home-page: http://github.com/dmerejkowsky/pycp
Author: Dimitri Merejkowsky
Author-email: d.merej@gmail.com
License: COPYING
Platform: UNKNOWN
Classifier: Environment :: Console
Classifier: License :: OSI Approved :: BSD License
Classifier: Operating System :: Unix
Classifier: Programming Language :: Python :: 3
Classifier: Topic :: System :: Shells
Requires-Dist: attrs
Provides-Extra: dev
Requires-Dist: path.py ; extra == 'dev'
Requires-Dist: pycodestyle ; extra == 'dev'
Requires-Dist: pyflakes ; extra == 'dev'
Requires-Dist: pylint ; extra == 'dev'
Requires-Dist: mccabe ; extra == 'dev'
Requires-Dist: pytest ; extra == 'dev'
Requires-Dist: pytest-mock ; extra == 'dev'
Requires-Dist: bumpversion ; extra == 'dev'
Requires-Dist: twine ; extra == 'dev'
Requires-Dist: wheel ; extra == 'dev'
